structlog_config/__init__.py
structlog_config/constants.py
structlog_config/env_config.py
structlog_config/environments.py
structlog_config/fastapi_access_logger.py
structlog_config/formatters.py
structlog_config/levels.py
structlog_config/packages.py
structlog_config/pytest_plugin.py
structlog_config/stdlib_logging.py
structlog_config/trace.py
structlog_config/warnings.py
structlog_config-0.8.0.dist-info/WHEEL
structlog_config-0.8.0.dist-info/METADATA
structlog_config-0.8.0.dist-info/RECORD
