Metadata-Version: 2.3
Name: structlog-config
Version: 0.8.0
Summary: A comprehensive structlog configuration with sensible defaults for development and production environments, featuring context management, exception formatting, and path prettification.
Keywords: logging,structlog,json-logging,structured-logging
Author: Michael Bianco
Author-email: Michael Bianco <mike@mikebian.co>
Requires-Dist: orjson>=3.10.15
Requires-Dist: python-decouple-typed>=3.11.0
Requires-Dist: fastapi-ipware>=0.1.1
Requires-Dist: structlog>=25.2.0
Requires-Dist: fastapi-ipware>=0.1.0 ; extra == 'fastapi'
Requires-Python: >=3.11
Project-URL: Repository, https://github.com/iloveitaly/structlog-config
Provides-Extra: fastapi
